pyxctsk/__init__.py
pyxctsk/__main__.py
pyxctsk/cli.py
pyxctsk/distance.py
pyxctsk/exceptions.py
pyxctsk/geojson.py
pyxctsk/optimization_config.py
pyxctsk/parser.py
pyxctsk/qrcode_encoding.py
pyxctsk/qrcode_enums.py
pyxctsk/qrcode_models.py
pyxctsk/qrcode_task.py
pyxctsk/route_optimization.py
pyxctsk/sss_calculations.py
pyxctsk/task.py
pyxctsk/task_distances.py
pyxctsk/turnpoint.py
pyxctsk/utils.py
pyxctsk-0.2.0.dist-info/LICENSE
pyxctsk-0.2.0.dist-info/METADATA
pyxctsk-0.2.0.dist-info/WHEEL
pyxctsk-0.2.0.dist-info/entry_points.txt
pyxctsk-0.2.0.dist-info/top_level.txt
pyxctsk-0.2.0.dist-info/RECORD
