Metadata-Version: 2.1
Name: pyxctsk
Version: 0.2.0
Summary: Python implementation of XCTrack's task format
Author-email: Simon Steiner <simonsteiner@users.noreply.github.com>
License: MIT
Project-URL: Repository, https://github.com/simonsteiner/pyxctsk
Classifier: Development Status :: 4 - Beta
Classifier: Intended Audience :: Developers
Classifier: License :: OSI Approved :: MIT License
Classifier: Programming Language :: Python :: 3
Classifier: Programming Language :: Python :: 3.8
Classifier: Programming Language :: Python :: 3.9
Classifier: Programming Language :: Python :: 3.10
Classifier: Programming Language :: Python :: 3.11
Classifier: Programming Language :: Python :: 3.12
Requires-Python: >=3.8
License-File: LICENSE
Requires-Dist: click>=8.2.0
Requires-Dist: geopy>=2.4.0
Requires-Dist: Pillow>=11.0.0
Requires-Dist: polyline>=2.0.0
Requires-Dist: pyproj>=3.7.0
Requires-Dist: pyzbar>=0.1.9
Requires-Dist: qrcode[pil]>=8.0.0
Requires-Dist: scipy>=1.16.0
Provides-Extra: analysis
Requires-Dist: numpy>=1.21.0; extra == "analysis"
Requires-Dist: geographiclib>=2.0; extra == "analysis"
Requires-Dist: matplotlib>=3.3.0; extra == "analysis"
Provides-Extra: dev
Requires-Dist: beautifulsoup4>=4.9.0; extra == "dev"
Requires-Dist: black>=21.0.0; extra == "dev"
Requires-Dist: flake8>=3.8.0; extra == "dev"
Requires-Dist: isort>=5.0.0; extra == "dev"
Requires-Dist: mypy>=0.800; extra == "dev"
Requires-Dist: pytest-cov>=2.0.0; extra == "dev"
Requires-Dist: pytest>=6.0.0; extra == "dev"
Requires-Dist: requests>=2.25.0; extra == "dev"
Provides-Extra: web
Requires-Dist: flask>=2.0.0; extra == "web"
